advanced_pid/__init__.py
advanced_pid/pid.py
advanced_pid/models/__init__.py
advanced_pid/models/mass_spring_damper.py
advanced_pid-0.0.8.dist-info/LICENSE
advanced_pid-0.0.8.dist-info/METADATA
advanced_pid-0.0.8.dist-info/WHEEL
advanced_pid-0.0.8.dist-info/top_level.txt
advanced_pid-0.0.8.dist-info/RECORD
