Metadata-Version: 2.1
Name: advanced-pid
Version: 0.0.8
Home-page: https://github.com/eadali/advanced-pid
Author: eadali
License: MIT
Project-URL: Documentation, https://advanced-pid.readthedocs.io/
Project-URL: Source Code, https://github.com/eadali/advanced-pid
Keywords: control theory,control,theory,engineering,pid,real,time
Classifier: Development Status :: 4 - Beta
Classifier: Intended Audience :: Developers
Classifier: Topic :: Software Development :: Build Tools
Classifier: License :: OSI Approved :: MIT License
Classifier: Programming Language :: Python :: 3
License-File: LICENSE
